corut/__about__.py
corut/__init__.py
corut/contenttypes.py
corut/shell/__init__.py
corut/shell/dotenv.py
corut/shell/pipupdater.py
corut/shell/utilssys.py
corut/vcs/__init__.py
corut/vcs/utilsgit.py
corut-1.0.1.dist-info/METADATA
corut-1.0.1.dist-info/WHEEL
corut-1.0.1.dist-info/RECORD
