Metadata-Version: 2.3
Name: corut
Version: 1.0.1
Summary: Desktop/Web applications and include needs for many devices.
Project-URL: Documentation, https://www.ibrahimcorut.com/repository/pypi-corut/overview
Project-URL: Source, https://www.ibrahimcorut.com/repository/pypi-corut/code/tree/main
Project-URL: Issues, https://www.ibrahimcorut.com/repository/pypi-corut/issues
Author-email: İbrahim CÖRÜT <ibrhmcorut@gmail.com>
License: MIT License
Keywords: corut,cörüt,ibrahim cörüt,tools,utils
Classifier: Intended Audience :: Developers
Classifier: License :: OSI Approved :: MIT License
Classifier: Programming Language :: Python :: 3.12
Classifier: Programming Language :: Python :: 3.13
Classifier: Programming Language :: Python :: Implementation :: PyPy
Requires-Python: >=3.12
Requires-Dist: gitpython
